swaggerhole/__init__.py
swaggerhole/__main__.py
swaggerhole/core/__init__.py
swaggerhole/core/misc.py
swaggerhole/core/regex_config.py
swaggerhole/core/research_secret.py
swaggerhole/core/swaggerhub_data.py
swaggerhole-1.1.dist-info/LICENSE
swaggerhole-1.1.dist-info/METADATA
swaggerhole-1.1.dist-info/WHEEL
swaggerhole-1.1.dist-info/entry_points.txt
swaggerhole-1.1.dist-info/top_level.txt
swaggerhole-1.1.dist-info/RECORD
