Metadata-Version: 2.1
Name: swaggerhole
Version: 1.1
Summary: Automate the process of retrieving secrets in the public APIs on swaggerHub
Home-page: https://github.com/Liodeus/swaggerHole
Author: Liodeus
License: GPL-3.0 License
Keywords: python,pentesting,secret,bugbounty,security
Platform: UNKNOWN
Classifier: Programming Language :: Python :: 3
Classifier: Topic :: Security
Classifier: Intended Audience :: Developers
Classifier: Intended Audience :: Information Technology
License-File: LICENSE
Requires-Dist: requests
Requires-Dist: whispers
